ateltasdk/VERSION
ateltasdk/__init__.py
ateltasdk/__main__.py
ateltasdk/base.py
ateltasdk/cli.py
ateltasdk/pose/draw.py
ateltasdk/pose/pose_matcher.py
ateltasdk/pose/pose_utils.py
ateltasdk/streamer.py
ateltasdk-0.1.2.dist-info/LICENSE
ateltasdk-0.1.2.dist-info/METADATA
ateltasdk-0.1.2.dist-info/WHEEL
ateltasdk-0.1.2.dist-info/entry_points.txt
ateltasdk-0.1.2.dist-info/RECORD
