Metadata-Version: 2.1
Name: ateltasdk
Version: 0.1.2
Summary: 
Author: anindyadeep
Requires-Python: >=3.9,<4.0
Classifier: Programming Language :: Python :: 3
Classifier: Programming Language :: Python :: 3.9
Classifier: Programming Language :: Python :: 3.10
Classifier: Programming Language :: Python :: 3.11
